loon_utils/__init__.py
loon_utils/convert_trackmate.py
loon_utils/main.py
loon_utils-0.0.7.dist-info/METADATA
loon_utils-0.0.7.dist-info/WHEEL
loon_utils-0.0.7.dist-info/entry_points.txt
loon_utils-0.0.7.dist-info/RECORD
