Metadata-Version: 2.4
Name: loon-utils
Version: 0.0.7
Summary: A python library for updating / converting data for use in Loon visualization
Project-URL: Homepage, https://github.com/visdesignlab/loon-utils
Author-email: Luke Schreiber <lucasjschreiber@gmail.com>, Devin Lange <devinscottlange@gmail.com>
License: MIT
Classifier: Environment :: Console
Classifier: Intended Audience :: Developers
Classifier: License :: OSI Approved :: MIT License
Classifier: Operating System :: OS Independent
Classifier: Programming Language :: Python
Classifier: Programming Language :: Python :: 3 :: Only
Classifier: Programming Language :: Python :: 3.13
Requires-Python: >=3.12
